taowa/__init__.py
taowa/win32.py
taowa/wx界面.py
taowa/以太坊.py
taowa/其它.py
taowa/数值.py
taowa/数据类型类.py
taowa/文件.py
taowa/文本.py
taowa/时间.py
taowa/系统.py
taowa/线程.py
taowa/编码.py
taowa/网页.py
taowa/装饰器.py
taowa/Skin/AERO
taowa/Skin/Adamant
taowa/Skin/Angel
taowa/Skin/AngelBSC
taowa/Skin/Aquanox
taowa/Skin/Areo
taowa/Skin/Asus
taowa/Skin/Black
taowa/Skin/Black01
taowa/Skin/Black04
taowa/Skin/CF_heilong
taowa/Skin/CF_heiqisi
taowa/Skin/CF_huimie
taowa/Skin/CF_huoqilin
taowa/Skin/CF_leishen
taowa/Skin/CF_lielong
taowa/Skin/CF_longling
taowa/Skin/CF_meiguijingling
taowa/Skin/CF_panlong
taowa/Skin/CF_potian
taowa/Skin/CF_sishen
taowa/Skin/CF_tulong
taowa/Skin/CHINA
taowa/Skin/Dogmax
taowa/Skin/FlatUI
taowa/Skin/Green1
taowa/Skin/IllumeCG
taowa/Skin/Itunes
taowa/Skin/KingMe
taowa/Skin/LOL_jiansheng
taowa/Skin/Longhorn
taowa/Skin/MAC
taowa/Skin/MSN
taowa/Skin/Mancity1
taowa/Skin/Office_2007
taowa/Skin/Pink1
taowa/Skin/QQ2008
taowa/Skin/QQ2009
taowa/Skin/QQ2009_1
taowa/Skin/QQ2009_2
taowa/Skin/QQ2009_3
taowa/Skin/QQ2010
taowa/Skin/QQ2011
taowa/Skin/QQ2015
taowa/Skin/QQ2015_1
taowa/Skin/QQGame
taowa/Skin/QQMusic3
taowa/Skin/QQTalkSHE
taowa/Skin/QQjinshuhui
taowa/Skin/QQliulanqi
taowa/Skin/QQmuisc
taowa/Skin/QQyingyin
taowa/Skin/QQyinyue
taowa/Skin/REAL
taowa/Skin/ShanMengzaiban
taowa/Skin/Skin.dll
taowa/Skin/Storm
taowa/Skin/TIM
taowa/Skin/TIM_1
taowa/Skin/VISTA
taowa/Skin/Vista1
taowa/Skin/WIN10
taowa/Skin/WIN10_2
taowa/Skin/WhiteFire
taowa/Skin/Win10_1
taowa/Skin/Win7
taowa/Skin/Win8SHE
taowa/Skin/Xenes
taowa/Skin/baise
taowa/Skin/baisejianyue
taowa/Skin/caihong
taowa/Skin/chengzhonghetang
taowa/Skin/chunbai
taowa/Skin/chunhei
taowa/Skin/chunjingpifu
taowa/Skin/compact
taowa/Skin/dongjingshishiguijinmu
taowa/Skin/duocaipifu
taowa/Skin/fengwochao
taowa/Skin/fenhongzhuti
taowa/Skin/gangtiexia
taowa/Skin/gaobiaolan
taowa/Skin/gaobiaolanbai
taowa/Skin/guohe
taowa/Skin/haibianzhuzhai
taowa/Skin/haizeiwang
taowa/Skin/heheheise
taowa/Skin/heheheise2
taowa/Skin/hehelvse
taowa-1.0.5.dist-info/METADATA
taowa-1.0.5.dist-info/WHEEL
taowa-1.0.5.dist-info/top_level.txt
taowa-1.0.5.dist-info/RECORD
