Metadata-Version: 2.1
Name: taowa
Version: 1.0.5
Summary: 建议使用python3.9版本,高版本可能需要自己提前安装一些模块
Home-page: UNKNOWN
Author: 陈炳强
Author-email: 99396686@qq.com
License: UNKNOWN
Platform: UNKNOWN
Classifier: Programming Language :: Python :: 3
Classifier: License :: OSI Approved :: MIT License
Classifier: Operating System :: OS Independent
Requires-Python: >=3.6
Requires-Dist: wxPython
Requires-Dist: web3
Requires-Dist: requests
Requires-Dist: PyExecjs
Requires-Dist: pywin32
